{
  "id": "module-2-gazebo/sensors",
  "title": "Simulating Sensors in Gazebo",
  "description": "Robots rely on sensors to perceive their environment. In simulation, we can model different types of sensors to mimic real-world sensor data. Here, we will explore simulating LiDAR, IMU, and depth cameras in Gazebo.",
  "source": "@site/docs/module-2-gazebo/sensors.mdx",
  "sourceDirName": "module-2-gazebo",
  "slug": "/module-2-gazebo/sensors",
  "permalink": "/Hackathon-Physical-AI-Humanoid-Book/docs/module-2-gazebo/sensors",
  "draft": false,
  "unlisted": false,
  "editUrl": "https://github.com/lotusf980/Hackathon-Physical-AI-Humanoid-Book/edit/main/docs/module-2-gazebo/sensors.mdx",
  "tags": [],
  "version": "current",
  "frontMatter": {
    "title": "Simulating Sensors in Gazebo"
  },
  "sidebar": "tutorialSidebar",
  "previous": {
    "title": "Physics Concepts in Robotics Simulation",
    "permalink": "/Hackathon-Physical-AI-Humanoid-Book/docs/module-2-gazebo/physics"
  },
  "next": {
    "title": "High-Fidelity Simulation with Unity",
    "permalink": "/Hackathon-Physical-AI-Humanoid-Book/docs/module-2-gazebo/unity"
  }
}